MANIFEST.in
README
setup.py
docbucket/__init__.py
docbucket/forms.py
docbucket/helpers.py
docbucket/models.py
docbucket/urls.py
docbucket/views.py
docbucket.egg-info/PKG-INFO
docbucket.egg-info/SOURCES.txt
docbucket.egg-info/dependency_links.txt
docbucket.egg-info/not-zip-safe
docbucket.egg-info/top_level.txt
docbucket/management/__init__.py
docbucket/management/commands/__init__.py
docbucket/management/commands/create_index.py
docbucket/management/commands/reindex_all.py
docbucket/media/docbucket/css/master.css
docbucket/media/docbucket/images/logo.png
docbucket/media/docbucket/js/docbucket.js
docbucket/media/docbucket/js/contrib/jquery-1.4.2.min.js
docbucket/media/docbucket/js/contrib/jquery-ui-1.8.6.custom.min.js
docbucket/templates/docbucket/base.html
docbucket/templates/docbucket/create.html
docbucket/templates/docbucket/document.html
docbucket/templates/docbucket/home.html
docbucket/templates/docbucket/list.html
docbucket/templates/docbucket/manage.html
docbucket/templates/docbucket/search.html
docbucket/templates/docbucket/show.html
examples/settings.py
examples/urls.py