Metadata-Version: 1.0
Name: docbucket
Version: 0.1
Summary: A simple document manager for individuals written with Django
Home-page: http://idevelop.org/p/docbucket/
Author: Antoine Millet
Author-email: antoine@inaps.org
License: GPL3
Keywords: django document mongodb
Platform: UNKNOWN
Classifier: Programming Language :: Python
